{
	"configurations" : 
	[
		{
			"directories" : 
			[
				{
					"build" : ".",
					"hasInstallRule" : true,
					"jsonFile" : "directory-.-Debug-0ad71585a6edab9006cf.json",
					"minimumCMakeVersion" : 
					{
						"string" : "3.16"
					},
					"projectIndex" : 0,
					"source" : ".",
					"targetIndexes" : 
					[
						0,
						1,
						2,
						3,
						4,
						5,
						6,
						7,
						8,
						9,
						10,
						11,
						12,
						13,
						14,
						15,
						16,
						17
					]
				}
			],
			"name" : "Debug",
			"projects" : 
			[
				{
					"directoryIndexes" : 
					[
						0
					],
					"name" : "course_217",
					"targetIndexes" : 
					[
						0,
						1,
						2,
						3,
						4,
						5,
						6,
						7,
						8,
						9,
						10,
						11,
						12,
						13,
						14,
						15,
						16,
						17
					]
				}
			],
			"targets" : 
			[
				{
					"directoryIndex" : 0,
					"id" : "all_aotstats::@6890427a1f51a3e7e1df",
					"jsonFile" : "target-all_aotstats-Debug-7c43fc34db733ee45a38.json",
					"name" : "all_aotstats",
					"projectIndex" : 0
				},
				{
					"directoryIndex" : 0,
					"id" : "all_qmllint::@6890427a1f51a3e7e1df",
					"jsonFile" : "target-all_qmllint-Debug-0d6727c46b8767b13029.json",
					"name" : "all_qmllint",
					"projectIndex" : 0
				},
				{
					"directoryIndex" : 0,
					"id" : "all_qmllint_json::@6890427a1f51a3e7e1df",
					"jsonFile" : "target-all_qmllint_json-Debug-ab2ec09ceffbb1e91e97.json",
					"name" : "all_qmllint_json",
					"projectIndex" : 0
				},
				{
					"directoryIndex" : 0,
					"id" : "all_qmllint_module::@6890427a1f51a3e7e1df",
					"jsonFile" : "target-all_qmllint_module-Debug-aed9f69984ecf42644b7.json",
					"name" : "all_qmllint_module",
					"projectIndex" : 0
				},
				{
					"directoryIndex" : 0,
					"id" : "all_qmltyperegistrations::@6890427a1f51a3e7e1df",
					"jsonFile" : "target-all_qmltyperegistrations-Debug-9622b8024c292de0346e.json",
					"name" : "all_qmltyperegistrations",
					"projectIndex" : 0
				},
				{
					"directoryIndex" : 0,
					"id" : "appcourse_217::@6890427a1f51a3e7e1df",
					"jsonFile" : "target-appcourse_217-Debug-75211d298c0a6a7538c9.json",
					"name" : "appcourse_217",
					"projectIndex" : 0
				},
				{
					"directoryIndex" : 0,
					"id" : "appcourse_217_autogen::@6890427a1f51a3e7e1df",
					"jsonFile" : "target-appcourse_217_autogen-Debug-720b1e7d284f9eeb0ca7.json",
					"name" : "appcourse_217_autogen",
					"projectIndex" : 0
				},
				{
					"directoryIndex" : 0,
					"id" : "appcourse_217_autogen_timestamp_deps::@6890427a1f51a3e7e1df",
					"jsonFile" : "target-appcourse_217_autogen_timestamp_deps-Debug-4a12615d44fa77de25eb.json",
					"name" : "appcourse_217_autogen_timestamp_deps",
					"projectIndex" : 0
				},
				{
					"directoryIndex" : 0,
					"id" : "appcourse_217_copy_qml::@6890427a1f51a3e7e1df",
					"jsonFile" : "target-appcourse_217_copy_qml-Debug-22e4b4fa60a94b7c9ff4.json",
					"name" : "appcourse_217_copy_qml",
					"projectIndex" : 0
				},
				{
					"directoryIndex" : 0,
					"id" : "appcourse_217_copy_res::@6890427a1f51a3e7e1df",
					"jsonFile" : "target-appcourse_217_copy_res-Debug-167a2b157a1a4ca07b41.json",
					"name" : "appcourse_217_copy_res",
					"projectIndex" : 0
				},
				{
					"directoryIndex" : 0,
					"id" : "appcourse_217_generate_qmlls_ini_file::@6890427a1f51a3e7e1df",
					"jsonFile" : "target-appcourse_217_generate_qmlls_ini_file-Debug-b82897bbcf19c6a86ef8.json",
					"name" : "appcourse_217_generate_qmlls_ini_file",
					"projectIndex" : 0
				},
				{
					"directoryIndex" : 0,
					"id" : "appcourse_217_qmlimportscan::@6890427a1f51a3e7e1df",
					"jsonFile" : "target-appcourse_217_qmlimportscan-Debug-c26430e28fd1e223225b.json",
					"name" : "appcourse_217_qmlimportscan",
					"projectIndex" : 0
				},
				{
					"directoryIndex" : 0,
					"id" : "appcourse_217_qmllint::@6890427a1f51a3e7e1df",
					"jsonFile" : "target-appcourse_217_qmllint-Debug-e94a56af258a50941e3a.json",
					"name" : "appcourse_217_qmllint",
					"projectIndex" : 0
				},
				{
					"directoryIndex" : 0,
					"id" : "appcourse_217_qmllint_json::@6890427a1f51a3e7e1df",
					"jsonFile" : "target-appcourse_217_qmllint_json-Debug-9b58986a3ed9b99226be.json",
					"name" : "appcourse_217_qmllint_json",
					"projectIndex" : 0
				},
				{
					"directoryIndex" : 0,
					"id" : "appcourse_217_qmllint_module::@6890427a1f51a3e7e1df",
					"jsonFile" : "target-appcourse_217_qmllint_module-Debug-a210ad4dd4d111e26cc5.json",
					"name" : "appcourse_217_qmllint_module",
					"projectIndex" : 0
				},
				{
					"directoryIndex" : 0,
					"id" : "appcourse_217_qmltyperegistration::@6890427a1f51a3e7e1df",
					"jsonFile" : "target-appcourse_217_qmltyperegistration-Debug-cc9fb0389715f41ebc3a.json",
					"name" : "appcourse_217_qmltyperegistration",
					"projectIndex" : 0
				},
				{
					"directoryIndex" : 0,
					"id" : "generate_qmlls_build_ini_file::@6890427a1f51a3e7e1df",
					"jsonFile" : "target-generate_qmlls_build_ini_file-Debug-448ff38e386e4e374023.json",
					"name" : "generate_qmlls_build_ini_file",
					"projectIndex" : 0
				},
				{
					"directoryIndex" : 0,
					"id" : "module_appcourse_217_aotstats_target::@6890427a1f51a3e7e1df",
					"jsonFile" : "target-module_appcourse_217_aotstats_target-Debug-6974894af441e7cd5068.json",
					"name" : "module_appcourse_217_aotstats_target",
					"projectIndex" : 0
				}
			]
		}
	],
	"kind" : "codemodel",
	"paths" : 
	{
		"build" : "C:/Users/Fillin/Documents/course_217/build",
		"source" : "C:/Users/Fillin/Documents/course_217"
	},
	"version" : 
	{
		"major" : 2,
		"minor" : 8
	}
}
